[
  [
    {
      "location": [
        48.06266997152855,
        11.362610772210829
      ],
      "dist_seconds": 3055,
      "intensity": 0.8
    },
    {
      "location": [
        48.06266997152855,
        11.398522333340855
      ],
      "dist_seconds": 3018,
      "intensity": 0.7000000000000001
    },
    {
      "location": [
        48.06266997152855,
        11.434433894470882
      ],
      "dist_seconds": -1,
      "intensity": 0.9
    },
    {
      "location": [
        48.06266997152855,
        11.47034545560091
      ],
      "dist_seconds": -1,
      "intensity": 1.0
    },
    {
      "location": [
        48.06266997152855,
        11.506257016730936
      ],
      "dist_seconds": 2859,
      "intensity": 0.7000000000000001
    },
    {
      "location": [
        48.06266997152855,
        11.542168577860963
      ],
      "dist_seconds": 2099,
      "intensity": 0.5
    },
    {
      "location": [
        48.06266997152855,
        11.57808013899099
      ],
      "dist_seconds": -1,
      "intensity": 1.0
    },
    {
      "location": [
        48.06266997152855,
        11.613991700121016
      ],
      "dist_seconds": 1334,
      "intensity": 0.1
    },
    {
      "location": [
        48.06266997152855,
        11.649903261251044
      ],
      "dist_seconds": 2117,
      "intensity": 0.5
    },
    {
      "location": [
        48.06266997152855,
        11.68581482238107
      ],
      "dist_seconds": 1801,
      "intensity": 0.30000000000000004
    }
  ],
  [
    {
      "location": [
        48.081221760999945,
        11.362610772210829
      ],
      "dist_seconds": 3655,
      "intensity": 0.9
    },
    {
      "location": [
        48.081221760999945,
        11.398522333340855
      ],
      "dist_seconds": 2975,
      "intensity": 0.7000000000000001
    },
    {
      "location": [
        48.081221760999945,
        11.434433894470882
      ],
      "dist_seconds": -1,
      "intensity": 1.0
    },
    {
      "location": [
        48.081221760999945,
        11.47034545560091
      ],
      "dist_seconds": 1872,
      "intensity": 0.30000000000000004
    },
    {
      "location": [
        48.081221760999945,
        11.506257016730936
      ],
      "dist_seconds": 2076,
      "intensity": 0.5
    },
    {
      "location": [
        48.081221760999945,
        11.542168577860963
      ],
      "dist_seconds": 1956,
      "intensity": 0.4
    },
    {
      "location": [
        48.081221760999945,
        11.57808013899099
      ],
      "dist_seconds": 2562,
      "intensity": 0.6000000000000001
    },
    {
      "location": [
        48.081221760999945,
        11.613991700121016
      ],
      "dist_seconds": 1405,
      "intensity": 0.1
    },
    {
      "location": [
        48.081221760999945,
        11.649903261251044
      ],
      "dist_seconds": 1795,
      "intensity": 0.30000000000000004
    },
    {
      "location": [
        48.081221760999945,
        11.68581482238107
      ],
      "dist_seconds": 2655,
      "intensity": 0.7000000000000001
    }
  ],
  [
    {
      "location": [
        48.09977355047134,
        11.362610772210829
      ],
      "dist_seconds": 3160,
      "intensity": 0.8
    },
    {
      "location": [
        48.09977355047134,
        11.398522333340855
      ],
      "dist_seconds": 2540,
      "intensity": 0.6000000000000001
    },
    {
      "location": [
        48.09977355047134,
        11.434433894470882
      ],
      "dist_seconds": 2745,
      "intensity": 0.7000000000000001
    },
    {
      "location": [
        48.09977355047134,
        11.47034545560091
      ],
      "dist_seconds": 1882,
      "intensity": 0.4
    },
    {
      "location": [
        48.09977355047134,
        11.506257016730936
      ],
      "dist_seconds": 1441,
      "intensity": 0.2
    },
    {
      "location": [
        48.09977355047134,
        11.542168577860963
      ],
      "dist_seconds": 868,
      "intensity": 0.0
    },
    {
      "location": [
        48.09977355047134,
        11.57808013899099
      ],
      "dist_seconds": 1116,
      "intensity": 0.0
    },
    {
      "location": [
        48.09977355047134,
        11.613991700121016
      ],
      "dist_seconds": 1783,
      "intensity": 0.30000000000000004
    },
    {
      "location": [
        48.09977355047134,
        11.649903261251044
      ],
      "dist_seconds": 1245,
      "intensity": 0.1
    },
    {
      "location": [
        48.09977355047134,
        11.68581482238107
      ],
      "dist_seconds": 3066,
      "intensity": 0.8
    }
  ],
  [
    {
      "location": [
        48.118325339942736,
        11.362610772210829
      ],
      "dist_seconds": 2608,
      "intensity": 0.6000000000000001
    },
    {
      "location": [
        48.118325339942736,
        11.398522333340855
      ],
      "dist_seconds": 3049,
      "intensity": 0.7000000000000001
    },
    {
      "location": [
        48.118325339942736,
        11.434433894470882
      ],
      "dist_seconds": 2623,
      "intensity": 0.7000000000000001
    },
    {
      "location": [
        48.118325339942736,
        11.47034545560091
      ],
      "dist_seconds": 1459,
      "intensity": 0.2
    },
    {
      "location": [
        48.118325339942736,
        11.506257016730936
      ],
      "dist_seconds": 1125,
      "intensity": 0.1
    },
    {
      "location": [
        48.118325339942736,
        11.542168577860963
      ],
      "dist_seconds": 752,
      "intensity": 0.0
    },
    {
      "location": [
        48.118325339942736,
        11.57808013899099
      ],
      "dist_seconds": 700,
      "intensity": 0.0
    },
    {
      "location": [
        48.118325339942736,
        11.613991700121016
      ],
      "dist_seconds": 919,
      "intensity": 0.0
    },
    {
      "location": [
        48.118325339942736,
        11.649903261251044
      ],
      "dist_seconds": 1733,
      "intensity": 0.30000000000000004
    },
    {
      "location": [
        48.118325339942736,
        11.68581482238107
      ],
      "dist_seconds": 1899,
      "intensity": 0.4
    }
  ],
  [
    {
      "location": [
        48.13687712941413,
        11.362610772210829
      ],
      "dist_seconds": 2426,
      "intensity": 0.6000000000000001
    },
    {
      "location": [
        48.13687712941413,
        11.398522333340855
      ],
      "dist_seconds": 2470,
      "intensity": 0.6000000000000001
    },
    {
      "location": [
        48.13687712941413,
        11.434433894470882
      ],
      "dist_seconds": 1909,
      "intensity": 0.4
    },
    {
      "location": [
        48.13687712941413,
        11.47034545560091
      ],
      "dist_seconds": 2154,
      "intensity": 0.5
    },
    {
      "location": [
        48.13687712941413,
        11.506257016730936
      ],
      "dist_seconds": 1218,
      "intensity": 0.1
    },
    {
      "location": [
        48.13687712941413,
        11.542168577860963
      ],
      "dist_seconds": 1077,
      "intensity": 0.0
    },
    {
      "location": [
        48.13687712941413,
        11.57808013899099
      ],
      "dist_seconds": 149,
      "intensity": 0.0
    },
    {
      "location": [
        48.13687712941413,
        11.613991700121016
      ],
      "dist_seconds": 874,
      "intensity": 0.0
    },
    {
      "location": [
        48.13687712941413,
        11.649903261251044
      ],
      "dist_seconds": 1992,
      "intensity": 0.4
    },
    {
      "location": [
        48.13687712941413,
        11.68581482238107
      ],
      "dist_seconds": 1946,
      "intensity": 0.4
    }
  ],
  [
    {
      "location": [
        48.15542891888552,
        11.362610772210829
      ],
      "dist_seconds": 4198,
      "intensity": 0.9
    },
    {
      "location": [
        48.15542891888552,
        11.398522333340855
      ],
      "dist_seconds": 2498,
      "intensity": 0.6000000000000001
    },
    {
      "location": [
        48.15542891888552,
        11.434433894470882
      ],
      "dist_seconds": 1522,
      "intensity": 0.2
    },
    {
      "location": [
        48.15542891888552,
        11.47034545560091
      ],
      "dist_seconds": 1515,
      "intensity": 0.2
    },
    {
      "location": [
        48.15542891888552,
        11.506257016730936
      ],
      "dist_seconds": -1,
      "intensity": 1.0
    },
    {
      "location": [
        48.15542891888552,
        11.542168577860963
      ],
      "dist_seconds": 1312,
      "intensity": 0.1
    },
    {
      "location": [
        48.15542891888552,
        11.57808013899099
      ],
      "dist_seconds": 876,
      "intensity": 0.0
    },
    {
      "location": [
        48.15542891888552,
        11.613991700121016
      ],
      "dist_seconds": 1235,
      "intensity": 0.1
    },
    {
      "location": [
        48.15542891888552,
        11.649903261251044
      ],
      "dist_seconds": 1456,
      "intensity": 0.2
    },
    {
      "location": [
        48.15542891888552,
        11.68581482238107
      ],
      "dist_seconds": 2414,
      "intensity": 0.6000000000000001
    }
  ],
  [
    {
      "location": [
        48.173980708356915,
        11.362610772210829
      ],
      "dist_seconds": 2241,
      "intensity": 0.5
    },
    {
      "location": [
        48.173980708356915,
        11.398522333340855
      ],
      "dist_seconds": 2125,
      "intensity": 0.5
    },
    {
      "location": [
        48.173980708356915,
        11.434433894470882
      ],
      "dist_seconds": 2290,
      "intensity": 0.5
    },
    {
      "location": [
        48.173980708356915,
        11.47034545560091
      ],
      "dist_seconds": 1446,
      "intensity": 0.2
    },
    {
      "location": [
        48.173980708356915,
        11.506257016730936
      ],
      "dist_seconds": 1900,
      "intensity": 0.4
    },
    {
      "location": [
        48.173980708356915,
        11.542168577860963
      ],
      "dist_seconds": 1745,
      "intensity": 0.30000000000000004
    },
    {
      "location": [
        48.173980708356915,
        11.57808013899099
      ],
      "dist_seconds": 1287,
      "intensity": 0.1
    },
    {
      "location": [
        48.173980708356915,
        11.613991700121016
      ],
      "dist_seconds": 1654,
      "intensity": 0.30000000000000004
    },
    {
      "location": [
        48.173980708356915,
        11.649903261251044
      ],
      "dist_seconds": 1740,
      "intensity": 0.30000000000000004
    },
    {
      "location": [
        48.173980708356915,
        11.68581482238107
      ],
      "dist_seconds": -1,
      "intensity": 1.0
    }
  ],
  [
    {
      "location": [
        48.19253249782831,
        11.362610772210829
      ],
      "dist_seconds": 2234,
      "intensity": 0.5
    },
    {
      "location": [
        48.19253249782831,
        11.398522333340855
      ],
      "dist_seconds": 3638,
      "intensity": 0.8
    },
    {
      "location": [
        48.19253249782831,
        11.434433894470882
      ],
      "dist_seconds": 3605,
      "intensity": 0.8
    },
    {
      "location": [
        48.19253249782831,
        11.47034545560091
      ],
      "dist_seconds": 1596,
      "intensity": 0.2
    },
    {
      "location": [
        48.19253249782831,
        11.506257016730936
      ],
      "dist_seconds": 2367,
      "intensity": 0.6000000000000001
    },
    {
      "location": [
        48.19253249782831,
        11.542168577860963
      ],
      "dist_seconds": 1487,
      "intensity": 0.2
    },
    {
      "location": [
        48.19253249782831,
        11.57808013899099
      ],
      "dist_seconds": 1582,
      "intensity": 0.2
    },
    {
      "location": [
        48.19253249782831,
        11.613991700121016
      ],
      "dist_seconds": 799,
      "intensity": 0.0
    },
    {
      "location": [
        48.19253249782831,
        11.649903261251044
      ],
      "dist_seconds": 1751,
      "intensity": 0.30000000000000004
    },
    {
      "location": [
        48.19253249782831,
        11.68581482238107
      ],
      "dist_seconds": -1,
      "intensity": 1.0
    }
  ],
  [
    {
      "location": [
        48.211084287299705,
        11.362610772210829
      ],
      "dist_seconds": 3374,
      "intensity": 0.8
    },
    {
      "location": [
        48.211084287299705,
        11.398522333340855
      ],
      "dist_seconds": 4187,
      "intensity": 0.9
    },
    {
      "location": [
        48.211084287299705,
        11.434433894470882
      ],
      "dist_seconds": 3815,
      "intensity": 0.9
    },
    {
      "location": [
        48.211084287299705,
        11.47034545560091
      ],
      "dist_seconds": -1,
      "intensity": 1.0
    },
    {
      "location": [
        48.211084287299705,
        11.506257016730936
      ],
      "dist_seconds": 2528,
      "intensity": 0.6000000000000001
    },
    {
      "location": [
        48.211084287299705,
        11.542168577860963
      ],
      "dist_seconds": 1974,
      "intensity": 0.4
    },
    {
      "location": [
        48.211084287299705,
        11.57808013899099
      ],
      "dist_seconds": 2069,
      "intensity": 0.4
    },
    {
      "location": [
        48.211084287299705,
        11.613991700121016
      ],
      "dist_seconds": 1203,
      "intensity": 0.1
    },
    {
      "location": [
        48.211084287299705,
        11.649903261251044
      ],
      "dist_seconds": 3065,
      "intensity": 0.8
    },
    {
      "location": [
        48.211084287299705,
        11.68581482238107
      ],
      "dist_seconds": 2873,
      "intensity": 0.7000000000000001
    }
  ],
  [
    {
      "location": [
        48.2296360767711,
        11.362610772210829
      ],
      "dist_seconds": 2616,
      "intensity": 0.7000000000000001
    },
    {
      "location": [
        48.2296360767711,
        11.398522333340855
      ],
      "dist_seconds": 3994,
      "intensity": 0.9
    },
    {
      "location": [
        48.2296360767711,
        11.434433894470882
      ],
      "dist_seconds": 3824,
      "intensity": 0.9
    },
    {
      "location": [
        48.2296360767711,
        11.47034545560091
      ],
      "dist_seconds": 3082,
      "intensity": 0.8
    },
    {
      "location": [
        48.2296360767711,
        11.506257016730936
      ],
      "dist_seconds": 4020,
      "intensity": 0.9
    },
    {
      "location": [
        48.2296360767711,
        11.542168577860963
      ],
      "dist_seconds": -1,
      "intensity": 1.0
    },
    {
      "location": [
        48.2296360767711,
        11.57808013899099
      ],
      "dist_seconds": 3231,
      "intensity": 0.8
    },
    {
      "location": [
        48.2296360767711,
        11.613991700121016
      ],
      "dist_seconds": -1,
      "intensity": 1.0
    },
    {
      "location": [
        48.2296360767711,
        11.649903261251044
      ],
      "dist_seconds": 4106,
      "intensity": 0.9
    },
    {
      "location": [
        48.2296360767711,
        11.68581482238107
      ],
      "dist_seconds": 2077,
      "intensity": 0.5
    }
  ]
]